wavely/__init__.py
wavely/base.py
wavely/exceptions.py
wavely/helpers.py
wavely/paths.py
wavely-0.3.dist-info/LICENSE
wavely-0.3.dist-info/METADATA
wavely-0.3.dist-info/WHEEL
wavely-0.3.dist-info/top_level.txt
wavely-0.3.dist-info/RECORD
