Metadata-Version: 2.2
Name: wavely
Version: 0.3
Summary: A small library for building curve coordinates from simple components
Author: jhunt
License: The MIT License (MIT)
Project-URL: Documentation, https://github.com/jhunt/wavely/blob/main/README.md
Project-URL: Issues, https://github.com/jhunt/wavely/issues
Project-URL: Source, https://github.com/jhunt/wavely
Classifier: Programming Language :: Python :: 3.9
Classifier: License :: OSI Approved :: MIT License
Classifier: Operating System :: OS Independent
Requires-Python: >=3.9
License-File: LICENSE
